app/__init__.py
app/core/__init__.py
app/core/eagle_di.py
app/core/serverless.py
app/core/transaction.py
eagle_di/__init__.py
eagle_di-5.0.1.dist-info/licenses/LICENSE
eagle_di-5.0.1.dist-info/METADATA
eagle_di-5.0.1.dist-info/WHEEL
eagle_di-5.0.1.dist-info/top_level.txt
eagle_di-5.0.1.dist-info/RECORD
