Metadata-Version: 2.4
Name: eagle-di
Version: 5.0.1
Summary: Lightweight Dependency Injection for FastAPI - Type hint-based, zero dependencies
Author-email: David Nguyen <david@example.com>
License: MIT
Project-URL: Homepage, https://github.com/DavidNguyen2212/eagle-di
Project-URL: Documentation, https://github.com/DavidNguyen2212/eagle-di#readme
Project-URL: Repository, https://github.com/DavidNguyen2212/eagle-di
Project-URL: Issues, https://github.com/DavidNguyen2212/eagle-di/issues
Keywords: fastapi,dependency-injection,di,ioc,decorators,serverless,lambda
Classifier: Development Status :: 5 - Production/Stable
Classifier: Framework :: FastAPI
Classifier: Intended Audience :: Developers
Classifier: License :: OSI Approved :: MIT License
Classifier: Operating System :: OS Independent
Classifier: Programming Language :: Python :: 3
Classifier: Programming Language :: Python :: 3.9
Classifier: Programming Language :: Python :: 3.10
Classifier: Programming Language :: Python :: 3.11
Classifier: Programming Language :: Python :: 3.12
Classifier: Topic :: Software Development :: Libraries :: Python Modules
Classifier: Typing :: Typed
Requires-Python: >=3.9
License-File: LICENSE
Requires-Dist: fastapi>=0.95.0
Provides-Extra: transaction
Requires-Dist: sqlalchemy[asyncio]>=2.0.0; extra == "transaction"
Provides-Extra: aws
Requires-Dist: mangum>=0.17.0; extra == "aws"
Provides-Extra: azure
Requires-Dist: azure-functions>=1.17.0; extra == "azure"
Provides-Extra: serverless
Requires-Dist: mangum>=0.17.0; extra == "serverless"
Requires-Dist: sqlalchemy[asyncio]>=2.0.0; extra == "serverless"
Provides-Extra: dev
Requires-Dist: pytest>=8.0.0; extra == "dev"
Requires-Dist: pytest-asyncio>=0.23.0; extra == "dev"
Requires-Dist: pytest-cov>=4.1.0; extra == "dev"
Requires-Dist: httpx>=0.27.0; extra == "dev"
Requires-Dist: uvicorn[standard]>=0.30.0; extra == "dev"
Requires-Dist: ruff>=0.3.0; extra == "dev"
Requires-Dist: mypy>=1.8.0; extra == "dev"
Dynamic: license-file
